bgdb/__init__.py
bgdb/bgdb.py
bgdb/client/__init__.py
bgdb/client/client.py
bgdb/search/__init__.py
bgdb/search/search.py
bgdb/utils/__init__.py
bgdb/utils/utils.py
bgdb-1.0.11.dist-info/LICENSE
bgdb-1.0.11.dist-info/METADATA
bgdb-1.0.11.dist-info/WHEEL
bgdb-1.0.11.dist-info/top_level.txt
bgdb-1.0.11.dist-info/RECORD
