Metadata-Version: 2.1
Name: bgdb
Version: 1.0.11
Summary: Python client for the BGDB
Home-page: https://github.com/ngleadall/bgdb_python_client
Author: Nicholas Gleadall
Author-email: ng384@cam.ac.uk
Project-URL: Bug Tracker, https://github.com/ngleadall/bgdb_python_client/issues
Classifier: Programming Language :: Python :: 3
Classifier: License :: OSI Approved :: GNU General Public License v3 or later (GPLv3+)
Classifier: Operating System :: OS Independent
Requires-Python: >=3.6
License-File: LICENSE
Requires-Dist: requests
Requires-Dist: python-dotenv
